flake8_annotations_complexity/__init__.py
flake8_annotations_complexity/ast_helpers.py
flake8_annotations_complexity/checker.py
flake8_annotations_complexity-0.1.0.dist-info/LICENSE
flake8_annotations_complexity-0.1.0.dist-info/METADATA
flake8_annotations_complexity-0.1.0.dist-info/WHEEL
flake8_annotations_complexity-0.1.0.dist-info/entry_points.txt
flake8_annotations_complexity-0.1.0.dist-info/top_level.txt
flake8_annotations_complexity-0.1.0.dist-info/RECORD
