Metadata-Version: 2.1
Name: flake8-annotations-complexity
Version: 0.1.0
Summary: A flake8 extension that checks for type annotations complexity
Home-page: https://github.com/best-doctor/flake8-annotations-complexity
Author: Ilya Lebedev
Author-email: melevir@gmail.com
License: MIT
Keywords: flake8 annotations
Classifier: Environment :: Console
Classifier: Framework :: Flake8
Classifier: Operating System :: OS Independent
Classifier: Topic :: Software Development :: Documentation
Classifier: Topic :: Software Development :: Libraries :: Python Modules
Classifier: Topic :: Software Development :: Quality Assurance
Classifier: Programming Language :: Python
Classifier: Programming Language :: Python :: 3.9
Classifier: Programming Language :: Python :: 3.10
Classifier: Programming Language :: Python :: 3.11
Requires-Python: >=3.9
License-File: LICENSE
Requires-Dist: flake8
